keel_ds/__init__.py
keel_ds/data/balanced/processed/australian.npz
keel_ds/data/balanced/processed/banana.npz
keel_ds/data/balanced/processed/bands.npz
keel_ds/data/balanced/processed/breast.npz
keel_ds/data/balanced/processed/bupa.npz
keel_ds/data/balanced/processed/chess.npz
keel_ds/data/balanced/processed/contraceptive.npz
keel_ds/data/balanced/processed/crx.npz
keel_ds/data/balanced/processed/german.npz
keel_ds/data/balanced/processed/hayes-roth.npz
keel_ds/data/balanced/processed/heart.npz
keel_ds/data/balanced/processed/housevotes.npz
keel_ds/data/balanced/processed/ionosphere.npz
keel_ds/data/balanced/processed/iris.npz
keel_ds/data/balanced/processed/led7digit.npz
keel_ds/data/balanced/processed/letter.npz
keel_ds/data/balanced/processed/magic.npz
keel_ds/data/balanced/processed/mammographic.npz
keel_ds/data/balanced/processed/marketing.npz
keel_ds/data/balanced/processed/monk-2.npz
keel_ds/data/balanced/processed/movement_libras.npz
keel_ds/data/balanced/processed/mushroom.npz
keel_ds/data/balanced/processed/optdigits.npz
keel_ds/data/balanced/processed/penbased.npz
keel_ds/data/balanced/processed/phoneme.npz
keel_ds/data/balanced/processed/pima.npz
keel_ds/data/balanced/processed/ring.npz
keel_ds/data/balanced/processed/saheart.npz
keel_ds/data/balanced/processed/satimage.npz
keel_ds/data/balanced/processed/segment.npz
keel_ds/data/balanced/processed/sonar.npz
keel_ds/data/balanced/processed/spambase.npz
keel_ds/data/balanced/processed/splice.npz
keel_ds/data/balanced/processed/tae.npz
keel_ds/data/balanced/processed/texture.npz
keel_ds/data/balanced/processed/tic-tac-toe.npz
keel_ds/data/balanced/processed/titanic.npz
keel_ds/data/balanced/processed/twonorm.npz
keel_ds/data/balanced/processed/vehicle.npz
keel_ds/data/balanced/processed/vowel.npz
keel_ds/data/balanced/processed/wdbc.npz
keel_ds/data/balanced/processed/wine.npz
keel_ds/data/balanced/processed/wisconsin.npz
keel_ds/data/balanced/raw/australian.dat
keel_ds/data/balanced/raw/banana.dat
keel_ds-0.2.5.dist-info/METADATA
keel_ds-0.2.5.dist-info/WHEEL
keel_ds-0.2.5.dist-info/RECORD
