Metadata-Version: 2.1
Name: keel-ds
Version: 0.2.5
Summary: KeelDS is a package to load some datasets from KEEL repository with some normalizations and with split and discretization options.
Home-page: https://github.com/maicondallg/KeelDS
Author: Maicondalllg
Author-email: maicon.dallagnol@unesp.br
Requires-Python: >=3.10,<4.0
Classifier: Programming Language :: Python :: 3
Classifier: Programming Language :: Python :: 3.10
Classifier: Programming Language :: Python :: 3.11
Classifier: Programming Language :: Python :: 3.12
Requires-Dist: numpy (==1.23.3)
Requires-Dist: pandas (>=2.1,<3.0)
Project-URL: Documentation, https://github.com/maicondallg/KeelDS#readme
Project-URL: Repository, https://github.com/maicondallg/KeelDS
